ims_mcp/__init__.py
ims_mcp/__main__.py
ims_mcp/server.py
ims_mcp/resources/bootstrap.md
ims_mcp-1.0.20.dist-info/licenses/LICENSE
ims_mcp-1.0.20.dist-info/METADATA
ims_mcp-1.0.20.dist-info/WHEEL
ims_mcp-1.0.20.dist-info/entry_points.txt
ims_mcp-1.0.20.dist-info/top_level.txt
ims_mcp-1.0.20.dist-info/RECORD
