Metadata-Version: 2.4
Name: ims-mcp
Version: 1.0.20
Summary: Model Context Protocol server for IMS (Instruction Management Systems)
Author: Igor Solomatov
License-Expression: MIT
Project-URL: Homepage, https://pypi.org/project/ims-mcp/
Keywords: mcp,ims,retrieval,rag,ai,llm,model-context-protocol,knowledge-base
Classifier: Development Status :: 4 - Beta
Classifier: Intended Audience :: Developers
Classifier: Programming Language :: Python :: 3
Classifier: Programming Language :: Python :: 3.10
Classifier: Programming Language :: Python :: 3.11
Classifier: Programming Language :: Python :: 3.12
Classifier: Topic :: Software Development :: Libraries :: Python Modules
Classifier: Topic :: Scientific/Engineering :: Artificial Intelligence
Requires-Python: >=3.10
License-File: LICENSE
Requires-Dist: r2r>=3.6.0
Requires-Dist: mcp>=1.0.0
Provides-Extra: dev
Requires-Dist: build>=1.0.0; extra == "dev"
Requires-Dist: twine>=4.0.0; extra == "dev"
Requires-Dist: pytest>=7.0.0; extra == "dev"
Dynamic: license-file
